lstenv/__init__.py
lstenv/cli.py
lstenv/core.py
lstenv-0.1.1.dist-info/licenses/LICENSE
lstenv-0.1.1.dist-info/METADATA
lstenv-0.1.1.dist-info/WHEEL
lstenv-0.1.1.dist-info/entry_points.txt
lstenv-0.1.1.dist-info/top_level.txt
lstenv-0.1.1.dist-info/RECORD
